script_utils_log_async/__init__.py
script_utils_log_async/helpers.py
script_utils_log_async/logging_setup.py
script_utils_log_async/py.typed
script_utils_log_async/setup_main.py
script_utils_log_async-0.2.9.dist-info/licenses/LICENSE
script_utils_log_async-0.2.9.dist-info/METADATA
script_utils_log_async-0.2.9.dist-info/WHEEL
script_utils_log_async-0.2.9.dist-info/top_level.txt
script_utils_log_async-0.2.9.dist-info/RECORD
