Metadata-Version: 2.4
Name: script_utils_log_async
Version: 0.2.9
Summary: Minimal shared utilities for logging and main wrapping
Author: Michal Buchman
Author-email: misobuchta@gmail.com
License: MIT
License-File: LICENSE
Dynamic: author
Dynamic: author-email
Dynamic: license
Dynamic: license-file
Dynamic: summary
